inpars/__init__.py
inpars/dataset.py
inpars/evaluate.py
inpars/filter.py
inpars/generate.py
inpars/generate_triples.py
inpars/inpars.py
inpars/prompt.py
inpars/rerank.py
inpars/train.py
inpars/utils.py
inpars-0.2.1.dist-info/LICENSE
inpars-0.2.1.dist-info/METADATA
inpars-0.2.1.dist-info/WHEEL
inpars-0.2.1.dist-info/top_level.txt
inpars-0.2.1.dist-info/RECORD
