Metadata-Version: 2.1
Name: inpars
Version: 0.2.1
Summary: InPars
Home-page: https://github.com/zetaalphavector/InPars
Author: Hugo Abonizio
Author-email: hugo.abonizio@gmail.com
License: LICENSE.txt
License-File: LICENSE
Requires-Dist: torch
Requires-Dist: pyserini (>=0.19)
Requires-Dist: transformers (>=4.0)
Requires-Dist: pyyaml (>=6.0)
Requires-Dist: ir-datasets (>=0.5)
Requires-Dist: ftfy (>=6.0)
Requires-Dist: accelerate (>=0.15)
